mcp_logseq/__init__.py
mcp_logseq/logseq.py
mcp_logseq/logseq.py.bak
mcp_logseq/server.py
mcp_logseq/tools.py
mcp_logseq-1.0.1.dist-info/METADATA
mcp_logseq-1.0.1.dist-info/WHEEL
mcp_logseq-1.0.1.dist-info/entry_points.txt
mcp_logseq-1.0.1.dist-info/RECORD
