Metadata-Version: 2.4
Name: mcp-logseq
Version: 1.0.1
Summary: MCP server to work with LogSeq via the local HTTP server
Project-URL: Homepage, https://github.com/ergut/mcp-logseq
Project-URL: Bug Reports, https://github.com/ergut/mcp-logseq/issues
Project-URL: Source, https://github.com/ergut/mcp-logseq
Author-email: Salih Ergüt <salih.ergut@oredata.com>
License-Expression: MIT
Keywords: knowledge-management,logseq,mcp,model-context-protocol
Classifier: Development Status :: 4 - Beta
Classifier: Intended Audience :: Developers
Classifier: License :: OSI Approved :: MIT License
Classifier: Programming Language :: Python :: 3
Classifier: Programming Language :: Python :: 3.11
Classifier: Programming Language :: Python :: 3.12
Classifier: Topic :: Software Development :: Libraries :: Python Modules
Classifier: Topic :: Text Processing
Requires-Python: >=3.11
Requires-Dist: mcp>=1.1.0
Requires-Dist: python-dotenv>=1.0.1
Requires-Dist: requests>=2.32.3
